nsdf/__init__.py
nsdf/constants.py
nsdf/model.py
nsdf/nsdfdata.py
nsdf/nsdfreader.py
nsdf/nsdfwriter.py
nsdf/util.py
nsdf/test/__init__.py
nsdf/test/print_stats.py
nsdf/test/profile_nan.py
nsdf/test/profile_write_dialects.py
nsdf/test/test_model.py
nsdf/test/test_nsdfdata.py
nsdf/test/test_nsdfreader.py
nsdf/test/test_nsdfwriter.py
nsdf/test/test_util.py
nsdf/test/util.py
nsdf-0.2.post1.dist-info/LICENSE
nsdf-0.2.post1.dist-info/METADATA
nsdf-0.2.post1.dist-info/WHEEL
nsdf-0.2.post1.dist-info/top_level.txt
nsdf-0.2.post1.dist-info/RECORD
