Metadata-Version: 2.1
Name: nsdf
Version: 0.2.post1
Summary: NSDF is the Neuroscience Simulation Data Format
Home-page: https://github.com/nsdf/nsdf
Author: Subhasis Ray and Chaitanya Chintaluri
Author-email: ray.subhasis@gmail.com
License: GPL 3
Download-URL: https://github.com/nsdf/nsdf/tarball/0.1
Keywords: neuroscience simulation format data
Platform: UNKNOWN
Classifier: Development Status :: 3 - Alpha
Classifier: Topic :: Scientific/Engineering :: Bio-Informatics
Classifier: Intended Audience :: Science/Research
Classifier: License :: OSI Approved :: GNU General Public License v3 or later (GPLv3+)
Requires-Dist: h5py (>=3.0.0)
